pycantoether/__init__.py
pycantoether/server.py
pycantoether/lib/__init__.py
pycantoether/lib/srv_interface/__init__.py
pycantoether/lib/srv_interface/base.py
pycantoether/lib/srv_interface/yachtd_raw.py
pycantoether-0.1.2.dist-info/licenses/LICENSE
pycantoether-0.1.2.dist-info/METADATA
pycantoether-0.1.2.dist-info/WHEEL
pycantoether-0.1.2.dist-info/entry_points.txt
pycantoether-0.1.2.dist-info/top_level.txt
pycantoether-0.1.2.dist-info/RECORD
