Metadata-Version: 2.4
Name: pycantoether
Version: 0.1.2
Summary: This is bridge between NMEA2000 and TCP server.
Author-email: Alexey Matveev <a.matveev@gmail.com>
License-Expression: Apache-2.0
Project-URL: documentation, https://github.com/shizacat/n2k-can2ether
Project-URL: repository, https://github.com/shizacat/n2k-can2ether
Classifier: Programming Language :: Python :: 3
Classifier: Operating System :: OS Independent
Requires-Python: >=3.9
License-File: LICENSE
Requires-Dist: python-can
Requires-Dist: python-can[gs_usb]
Requires-Dist: serial
Requires-Dist: pyserial
Requires-Dist: pyusb
Provides-Extra: dev
Requires-Dist: pytest; extra == "dev"
Requires-Dist: pytest-cov; extra == "dev"
Requires-Dist: pytest-asyncio; extra == "dev"
Dynamic: license-file
